README.rst
setup.py
indicium/ldap/__init__.py
indicium/ldap/test.py
indicium_ldap.egg-info/PKG-INFO
indicium_ldap.egg-info/SOURCES.txt
indicium_ldap.egg-info/dependency_links.txt
indicium_ldap.egg-info/requires.txt
indicium_ldap.egg-info/top_level.txt