Metadata-Version: 1.1
Name: indicium-ldap
Version: 0.1.0a0
Summary: Generic key-value interface to a LDAP directory
Home-page: https://github.com/aperezdc/indicium-ldap
Author: Adrián Pérez de Castro
Author-email: aperez@igalia.com
License: ['GPLv3', 'Apache-2.0']
Platform: UNKNOWN
Classifier: Development Status :: 3 - Alpha
Classifier: Intended Audience :: Developers
Classifier: Natural Language :: English
Classifier: Programming Language :: Python :: 3.4
Classifier: Programming Language :: Python :: 3.5
Classifier: Programming Language :: Python
Classifier: Operating System :: OS Independent
Classifier: License :: OSI Approved :: GNU General Public License v3 (GPLv3)
Classifier: License :: OSI Approved :: Apache Software License
